{"aid": 13257, "type": "TV Series", "episodecount": 13, "title": "\u305d\u3089\u3088\u308a\u3082\u3068\u304a\u3044\u3070\u3057\u3087 / Yorimoi / \u5b87\u5b99\u3088\u308a\u3082\u9060\u3044\u5834\u6240", "date": {"start": "2017-12-29", "end": "2018-03-27"}, "cast": ["Iguchi Yuka", "Hanazawa Kana", "Minase Inori", "Hayami Saori", "Hikasa Youko", "Hondo Kaede", "Oohara Sayaka", "Noto Mamiko", "Kanemoto Hisako", "Lynn", "Honda Takako", "Endou Aya", "Komatsu Mikako", "Fukushima Jun", "Matsuoka Yoshitsugu", "Asumi Kana", "Terasoma Masaki", "Kayano Ai", "Minase Inori", "Kanemoto Hisako"], "company": ["Madhouse"], "picture": ["221627.jpg", "151404.jpg", "147835.jpg", "147834.jpg", "209466.jpg", "209465.jpg", "209463.jpg", "209467.jpg", "210643.jpg", "210646.jpg", "210647.jpg", "210642.jpg", "210645.jpg", "210644.jpg", "211693.jpg", "212578.jpg", "212579.jpg", "212576.jpg", "212575.jpg", "212577.jpg", "212574.jpg", "216288.jpg", "217623.jpg", "217624.jpg"]}
