{"aid": 14819, "type": "TV Series", "episodecount": 24, "title": "\u4e03\u3064\u306e\u5927\u7f6a \u795e\u3005\u306e\u9006\u9c57", "date": {"start": "2019-10-09", "end": "2020-03-25"}, "cast": ["Kaji Yuuki", "Amamiya Sora", "Kuno Misaki", "Yuuki Aoi", "Suzuki Tatsuhisa", "Miyano Mamoru", "Fukuyama Jun", "Kimura Ryouhei", "Uchida Yuuya", "Konishi Katsuyuki", "Nishi Rintarou", "Sakamoto Maaya", "Takagi Yuuhei", "Sugita Tomokazu", "Sakurai Takahiro", "Nishi Rintarou", "Kamiya Hiroshi", "Yahagi Sayuri", "Touchi Hiroki", "Iwasaki Hiroshi", "Kobayashi Yuusuke", "Kaji Yuuki", "Takagaki Ayahi", "Ono Daisuke", "Konishi Katsuyuki", "Satou Rina", "Mao", "Tsuda Kenjirou", "Yano Shougo", "Morohoshi Sumire", "Nakata Jouji", "Horie Shun", "Tsuruoka Satoshi", "Fuji Shinshuu", "Ishida Akira", "Fujiwara Keiji", "Yuuki Aoi", "Fukuyama Jun", "Amamiya Sora"], "company": null, "picture": ["232356.jpg", "160542.jpg", "214077.jpg", "160545.jpg", "214078.jpg", "163863.jpg", "162940.jpg", "68141.png", "164198.jpg", "165232.jpg", "165231.jpg", "165235.jpg", "171207.jpg", "68140.png", "214080.jpg", "216565.jpg", "165233.jpg", "169094.jpg", "169096.jpg", "204411.jpg", "210966.jpg", "210967.jpg", "210970.jpg", "210965.jpg", "210972.jpg", "210969.jpg", "217222.jpg", "214051.jpg", "210968.jpg", "210971.jpg", "214015.jpg", "213931.jpg", "243808.jpg", "243988.jpg", "241461.jpg", "241462.jpg", "243987.jpg", "241446.jpg", "241455.jpg", "241459.jpg", "241460.jpg", "241463.jpg", "243854.jpg", "68438.png", "243904.jpg", "243989.jpg"]}
