<?xml version="1.0" encoding="UTF-8"?><anime id="14876" restricted="false">
<type>Movie</type>
<episodecount>1</episodecount>
<startdate>2019-01-11</startdate>
<enddate>2019-01-11</enddate>
<titles>
<title xml:lang="x-zht" type="main">Bai She: Yuan Qi</title>
<title xml:lang="en" type="synonym">White Snake</title>
<title xml:lang="zh-Hans" type="official">白蛇: 缘起</title>
</titles>
<description>The story follows the Chinese fable the Legend of the White Snake and focuses on a hunter and a snake disguised as a human hunter.
Source: Wikipedia</description>
<ratings>
<permanent count="17">6.83</permanent>
<temporary count="17">6.44</temporary>
</ratings>
<picture>232958.jpg</picture>
<resources>
<resource type="2">
<externalentity>
<identifier>38740</identifier>
</externalentity>
</resource>
<resource type="6">
<externalentity>
<identifier>White_Snake_(film)</identifier>
</externalentity>
</resource>
<resource type="20">
<externalentity>
<identifier>白蛇：缘起</identifier>
</externalentity>
</resource>
<resource type="33">
<externalentity>
<identifier>白蛇：缘起</identifier>
</externalentity>
</resource>
</resources>
<tags>
<tag id="6152" parentid="6173" weight="0" localspoiler="false" globalspoiler="false" verified="true" update="2014-09-10">
<name>Chinese production</name>
</tag>
<tag id="6173" weight="0" localspoiler="false" globalspoiler="false" verified="true" update="2014-09-24">
<name>origin</name>
</tag>
</tags>
<episodes>
<episode id="215955" update="2019-04-22">
<epno type="1">1</epno>
<length>100</length>
<airdate>2019-01-11</airdate>
<title xml:lang="en">Complete Movie</title>
</episode>
</episodes>
</anime>
